{".class": "MypyFile", "_fullname": "wandb.plot.bar", "is_partial_stub_package": false, "is_stub": false, "names": {".class": "SymbolTable", "__doc__": {".class": "SymbolTableNode", "kind": "Gdef", "node": {".class": "Var", "flags": ["is_ready"], "fullname": "wandb.plot.bar.__doc__", "name": "__doc__", "type": "builtins.str"}}, "__file__": {".class": "SymbolTableNode", "kind": "Gdef", "node": {".class": "Var", "flags": ["is_ready"], "fullname": "wandb.plot.bar.__file__", "name": "__file__", "type": "builtins.str"}}, "__name__": {".class": "SymbolTableNode", "kind": "Gdef", "node": {".class": "Var", "flags": ["is_ready"], "fullname": "wandb.plot.bar.__name__", "name": "__name__", "type": "builtins.str"}}, "__package__": {".class": "SymbolTableNode", "kind": "Gdef", "node": {".class": "Var", "flags": ["is_ready"], "fullname": "wandb.plot.bar.__package__", "name": "__package__", "type": "builtins.str"}}, "bar": {".class": "SymbolTableNode", "kind": "Gdef", "node": {".class": "FuncDef", "arg_kinds": [0, 0, 0, 1], "arg_names": ["table", "label", "value", "title"], "flags": [], "fullname": "wandb.plot.bar.bar", "name": "bar", "type": null}}, "wandb": {".class": "SymbolTableNode", "cross_ref": "wandb", "kind": "Gdef"}}, "path": "/home/ninnart/anaconda3/envs/torch_cuda11/lib/python3.8/site-packages/wandb/plot/bar.py"}