{".class": "MypyFile", "_fullname": "wandb.sdk_py27.lib.sparkline", "is_partial_stub_package": false, "is_stub": false, "names": {".class": "SymbolTable", "__doc__": {".class": "SymbolTableNode", "kind": "Gdef", "node": {".class": "Var", "flags": ["is_ready"], "fullname": "wandb.sdk_py27.lib.sparkline.__doc__", "name": "__doc__", "type": "builtins.str"}}, "__file__": {".class": "SymbolTableNode", "kind": "Gdef", "node": {".class": "Var", "flags": ["is_ready"], "fullname": "wandb.sdk_py27.lib.sparkline.__file__", "name": "__file__", "type": "builtins.str"}}, "__name__": {".class": "SymbolTableNode", "kind": "Gdef", "node": {".class": "Var", "flags": ["is_ready"], "fullname": "wandb.sdk_py27.lib.sparkline.__name__", "name": "__name__", "type": "builtins.str"}}, "__package__": {".class": "SymbolTableNode", "kind": "Gdef", "node": {".class": "Var", "flags": ["is_ready"], "fullname": "wandb.sdk_py27.lib.sparkline.__package__", "name": "__package__", "type": "builtins.str"}}, "isfinite": {".class": "SymbolTableNode", "kind": "Gdef", "node": {".class": "FuncDef", "arg_kinds": [0], "arg_names": ["f"], "flags": [], "fullname": "wandb.sdk_py27.lib.sparkline.isfinite", "name": "isfinite", "type": null}}, "math": {".class": "SymbolTableNode", "cross_ref": "math", "kind": "Gdef"}, "spark_chars": {".class": "SymbolTableNode", "kind": "Gdef", "node": {".class": "Var", "flags": ["is_ready"], "fullname": "wandb.sdk_py27.lib.sparkline.spark_chars", "name": "spark_chars", "type": "builtins.str"}}, "sparkify": {".class": "SymbolTableNode", "kind": "Gdef", "node": {".class": "FuncDef", "arg_kinds": [0], "arg_names": ["series"], "flags": [], "fullname": "wandb.sdk_py27.lib.sparkline.sparkify", "name": "sparkify", "type": null}}}, "path": "/home/ninnart/anaconda3/envs/torch_cuda11/lib/python3.8/site-packages/wandb/sdk_py27/lib/sparkline.py"}