{"data_mtime": 1625189399, "dep_lines": [6, 8, 10, 11, 1, 1, 1, 1, 1, 1, 1, 1, 1, 1, 1, 1, 1, 1, 1, 1, 1, 1, 1, 1, 1, 1, 1, 1, 1, 1, 1, 1, 1], "dep_prios": [5, 5, 10, 5, 5, 20, 20, 20, 20, 20, 20, 20, 20, 20, 20, 20, 20, 20, 20, 20, 20, 20, 20, 20, 20, 20, 30, 30, 30, 30, 30, 30, 30], "dependencies": ["typing", "torch", "torch._linalg_utils", "torch.overrides", "builtins", "inspect", "logging", "contextlib", "functools", "threading", "collections", "pickle", "warnings", "torch.nn.functional", "re", "torch.nn.intrinsic.qat", "torch.nn", "operator", "torch.nn.qat", "enum", "torch.nn.quantized", "torch.nn.intrinsic", "torch.nn.quantized.dynamic", "torch.nn.intrinsic.quantized", "itertools", "copy", "abc", "torch._C", "torch._C._VariableFunctions", "torch.jit", "torch.sparse", "torch.tensor", "torch.types"], "hash": "c9138273570c32ab0aff51c2af84ae165f87e4751cadc79385a73f4ba98f5cff", "id": "torch._lowrank", "ignore_all": true, "interface_hash": "25e82fbd524a8e9dfa089d1ffbacb416885adcaaa9a162414493142ce5b1d44a", "mtime": 1607370118, "options": {"allow_redefinition": false, "allow_untyped_globals": false, "always_false": [], "always_true": [], "bazel": false, "check_untyped_defs": false, "disallow_any_decorated": false, "disallow_any_explicit": false, "disallow_any_expr": false, "disallow_any_generics": false, "disallow_any_unimported": false, "disallow_incomplete_defs": false, "disallow_subclassing_any": false, "disallow_untyped_calls": false, "disallow_untyped_decorators": false, "disallow_untyped_defs": false, "follow_imports": "normal", "follow_imports_for_stubs": false, "ignore_errors": false, "ignore_missing_imports": false, "implicit_reexport": true, "local_partial_types": false, "mypyc": false, "no_implicit_optional": false, "platform": "linux", "plugins": [], "show_none_errors": true, "strict_equality": false, "strict_optional": true, "strict_optional_whitelist": null, "warn_no_return": true, "warn_return_any": false, "warn_unreachable": false, "warn_unused_ignores": false}, "path": "/home/ninnart/anaconda3/envs/torch_cuda11/lib/python3.8/site-packages/torch/_lowrank.py", "plugin_data": null, "size": 10349, "suppressed": [], "version_id": "0.790"}